api_descstats_csv/__init__.py
api_descstats_csv/__main__.py
api_descstats_csv/create_tes_dataset.py
api_descstats_csv/create_tes_json.py
api_descstats_csv/utils.py
api_descstats_csv-0.1.3.dist-info/entry_points.txt
api_descstats_csv-0.1.3.dist-info/LICENSE
api_descstats_csv-0.1.3.dist-info/WHEEL
api_descstats_csv-0.1.3.dist-info/METADATA
api_descstats_csv-0.1.3.dist-info/RECORD
