Metadata-Version: 2.1
Name: api-descstats-csv
Version: 0.1.3
Summary: Calculate simple descreptive stats from csv with Python with cli or  import respecting the limit of 512 MB 
Home-page: https://gitlab.com/felipeffm/api_desc_stats_csv
License: MIT
Author: -
Author-email: felipefm@id.uff.br
Requires-Python: >=3.9,<4.0
Classifier: License :: OSI Approved :: MIT License
Classifier: Programming Language :: Python :: 3
Classifier: Programming Language :: Python :: 3.10
Classifier: Programming Language :: Python :: 3.9
Requires-Dist: numpy (>=1.23.1,<2.0.0)
Requires-Dist: pandas (>=1.4.3,<2.0.0)
Requires-Dist: pyarrow (>=8.0.0,<9.0.0)
Requires-Dist: pytest (>=7.1.2,<8.0.0)
Requires-Dist: rich (>=10.14.0,<11.0.0)
Requires-Dist: tqdm (>=4.64.0,<5.0.0)
Requires-Dist: typer[all] (>=0.4.0,<0.5.0)
Project-URL: Repository, https://gitlab.com/felipeffm/api_desc_stats_csv
